stats_advanced/__init__.py
stats_advanced/stats_advanced.py
stats_advanced-0.0.8.dist-info/METADATA
stats_advanced-0.0.8.dist-info/WHEEL
stats_advanced-0.0.8.dist-info/top_level.txt
stats_advanced-0.0.8.dist-info/RECORD
